{
  "captured_at": "2026-06-18T14:22:43+08:00",
  "items": [
    {
      "code": "511010",
      "name": "国债ETF",
      "market_cap": 4990000000.0,
      "avg_turnover_20d": 434381423.0,
      "turnover_1d": 576117712.0,
      "premium_pct": 0.08,
      "tracking_dispersion": null,
      "fee": {
        "management_fee": 0.0015,
        "custody_fee": 0.0005,
        "expense_ratio": 0.002
      },
      "purchase_status": "可申购",
      "cross_validation": {
        "status": "single_source",
        "sources": [
          "westock"
        ],
        "fields": {
          "price": {
            "westock": 141.43,
            "akshare": null,
            "threshold": 0.003,
            "status": "single_source",
            "difference": null
          },
          "iopv": {
            "westock": 141.31,
            "akshare": null,
            "threshold": 0.005,
            "westock_basis": "published_nav",
            "akshare_basis": "realtime_iopv",
            "status": "single_source",
            "difference": null
          },
          "premium": {
            "westock": 0.0008491968013586426,
            "akshare": null,
            "threshold": 0.005,
            "westock_basis": "published_nav",
            "akshare_basis": "realtime_iopv",
            "status": "single_source",
            "difference": null
          },
          "market_cap": {
            "westock": 4990000000.0,
            "akshare": null,
            "threshold": 0.15,
            "status": "single_source",
            "difference": null
          }
        },
        "critical_conflicts": [],
        "scale_conflict": false
      },
      "product_events": [],
      "product_risk": {
        "level": "info",
        "alerts": [],
        "trends": {
          "observations": 1
        },
        "automatic_replacement": false
      }
    },
    {
      "code": "510300",
      "name": "沪深300ETF",
      "market_cap": 134870000000.0,
      "avg_turnover_20d": 4115108928.0,
      "turnover_1d": 5546147845.0,
      "premium_pct": 0.05,
      "tracking_dispersion": 0.023424,
      "fee": {
        "management_fee": 0.0015,
        "custody_fee": 0.0005,
        "expense_ratio": 0.002
      },
      "purchase_status": "可申购",
      "cross_validation": {
        "status": "partial",
        "sources": [
          "akshare",
          "westock"
        ],
        "fields": {
          "price": {
            "westock": 4.98,
            "akshare": 4.981,
            "threshold": 0.003,
            "difference": 0.00020076,
            "status": "verified"
          },
          "iopv": {
            "westock": 4.91,
            "akshare": 4.9787,
            "threshold": 0.005,
            "westock_basis": "published_nav",
            "akshare_basis": "realtime_iopv",
            "difference": 0.01379878,
            "status": "not_comparable"
          },
          "premium": {
            "westock": 0.014256619144602967,
            "akshare": 0.00046196798361020086,
            "threshold": 0.005,
            "westock_basis": "published_nav",
            "akshare_basis": "realtime_iopv",
            "difference": 0.01379465,
            "status": "not_comparable"
          },
          "market_cap": {
            "westock": 134870000000.0,
            "akshare": 134897373193.0,
            "threshold": 0.15,
            "difference": 0.00020292,
            "status": "verified"
          }
        },
        "critical_conflicts": [],
        "scale_conflict": false
      },
      "product_events": [],
      "product_risk": {
        "level": "info",
        "alerts": [],
        "trends": {
          "observations": 1
        },
        "automatic_replacement": false
      }
    },
    {
      "code": "512890",
      "name": "红利低波ETF",
      "market_cap": 32317000000.0,
      "avg_turnover_20d": 833372470.0,
      "turnover_1d": 1319116247.0,
      "premium_pct": -0.01,
      "tracking_dispersion": null,
      "fee": {
        "management_fee": 0.005,
        "custody_fee": 0.001,
        "expense_ratio": 0.006
      },
      "purchase_status": "可申购",
      "cross_validation": {
        "status": "conflict",
        "sources": [
          "akshare",
          "westock"
        ],
        "fields": {
          "price": {
            "westock": 1.11,
            "akshare": 1.114,
            "threshold": 0.003,
            "difference": 0.00359066,
            "status": "conflict"
          },
          "iopv": {
            "westock": 1.14,
            "akshare": 1.1141,
            "threshold": 0.005,
            "westock_basis": "published_nav",
            "akshare_basis": "realtime_iopv",
            "difference": 0.0227193,
            "status": "not_comparable"
          },
          "premium": {
            "westock": -0.02631578947368407,
            "akshare": -8.975854950188378e-05,
            "threshold": 0.005,
            "westock_basis": "published_nav",
            "akshare_basis": "realtime_iopv",
            "difference": 0.02622603,
            "status": "not_comparable"
          },
          "market_cap": {
            "westock": 32317000000.0,
            "akshare": 32317263342.0,
            "threshold": 0.15,
            "difference": 8.15e-06,
            "status": "verified"
          }
        },
        "critical_conflicts": [
          "price"
        ],
        "scale_conflict": false
      },
      "product_events": [],
      "product_risk": {
        "level": "info",
        "alerts": [],
        "trends": {
          "observations": 1
        },
        "automatic_replacement": false
      }
    },
    {
      "code": "510500",
      "name": "中证500ETF",
      "market_cap": 40497000000.0,
      "avg_turnover_20d": 3242680054.0,
      "turnover_1d": 1807296920.0,
      "premium_pct": 0.16,
      "tracking_dispersion": null,
      "fee": {
        "management_fee": 0.0015,
        "custody_fee": 0.0005,
        "expense_ratio": 0.002
      },
      "purchase_status": "可申购",
      "cross_validation": {
        "status": "partial",
        "sources": [
          "akshare",
          "westock"
        ],
        "fields": {
          "price": {
            "westock": 8.85,
            "akshare": 8.847,
            "threshold": 0.003,
            "difference": 0.00033898,
            "status": "verified"
          },
          "iopv": {
            "westock": 8.64,
            "akshare": 8.8329,
            "threshold": 0.005,
            "westock_basis": "published_nav",
            "akshare_basis": "realtime_iopv",
            "difference": 0.02183881,
            "status": "not_comparable"
          },
          "premium": {
            "westock": 0.024305555555555358,
            "akshare": 0.0015963047243825468,
            "threshold": 0.005,
            "westock_basis": "published_nav",
            "akshare_basis": "realtime_iopv",
            "difference": 0.02270925,
            "status": "not_comparable"
          },
          "market_cap": {
            "westock": 40497000000.0,
            "akshare": 40506597324.0,
            "threshold": 0.15,
            "difference": 0.00023693,
            "status": "verified"
          }
        },
        "critical_conflicts": [],
        "scale_conflict": false
      },
      "product_events": [],
      "product_risk": {
        "level": "info",
        "alerts": [],
        "trends": {
          "observations": 1
        },
        "automatic_replacement": false
      }
    },
    {
      "code": "518880",
      "name": "黄金ETF",
      "market_cap": 96583000000.0,
      "avg_turnover_20d": 3203614412.0,
      "turnover_1d": 2227536242.0,
      "premium_pct": -0.02,
      "tracking_dispersion": null,
      "fee": {
        "management_fee": 0.005,
        "custody_fee": 0.001,
        "expense_ratio": 0.006
      },
      "purchase_status": "可申购",
      "cross_validation": {
        "status": "partial",
        "sources": [
          "akshare",
          "westock"
        ],
        "fields": {
          "price": {
            "westock": 8.89,
            "akshare": 8.904,
            "threshold": 0.003,
            "difference": 0.00157233,
            "status": "verified"
          },
          "iopv": {
            "westock": 8.96,
            "akshare": 8.906,
            "threshold": 0.005,
            "westock_basis": "published_nav",
            "akshare_basis": "realtime_iopv",
            "difference": 0.00602679,
            "status": "not_comparable"
          },
          "premium": {
            "westock": -0.0078125,
            "akshare": -0.00022456770716383634,
            "threshold": 0.005,
            "westock_basis": "published_nav",
            "akshare_basis": "realtime_iopv",
            "difference": 0.00758793,
            "status": "not_comparable"
          },
          "market_cap": {
            "westock": 96583000000.0,
            "akshare": 96680886823.0,
            "threshold": 0.15,
            "difference": 0.00101247,
            "status": "verified"
          }
        },
        "critical_conflicts": [],
        "scale_conflict": false
      },
      "product_events": [],
      "product_risk": {
        "level": "info",
        "alerts": [],
        "trends": {
          "observations": 1
        },
        "automatic_replacement": false
      }
    },
    {
      "code": "513500",
      "name": "标普500ETF",
      "market_cap": 25465000000.0,
      "avg_turnover_20d": 472214401.0,
      "turnover_1d": 270772351.0,
      "premium_pct": 7.21,
      "tracking_dispersion": null,
      "fee": {
        "management_fee": 0.006,
        "custody_fee": 0.002,
        "expense_ratio": 0.008
      },
      "purchase_status": "不可申购",
      "cross_validation": {
        "status": "partial",
        "sources": [
          "akshare",
          "westock"
        ],
        "fields": {
          "price": {
            "westock": 2.56,
            "akshare": 2.564,
            "threshold": 0.003,
            "difference": 0.00156006,
            "status": "verified"
          },
          "iopv": {
            "westock": 2.43,
            "akshare": 2.3916,
            "threshold": 0.005,
            "westock_basis": "published_nav",
            "akshare_basis": "realtime_iopv",
            "difference": 0.01580247,
            "status": "not_comparable"
          },
          "premium": {
            "westock": 0.05349794238683114,
            "akshare": 0.07208563304900495,
            "threshold": 0.005,
            "westock_basis": "published_nav",
            "akshare_basis": "realtime_iopv",
            "difference": 0.01858769,
            "status": "not_comparable"
          },
          "market_cap": {
            "westock": 25465000000.0,
            "akshare": 25464721186.0,
            "threshold": 0.15,
            "difference": 1.095e-05,
            "status": "verified"
          }
        },
        "critical_conflicts": [],
        "scale_conflict": false
      },
      "product_events": [],
      "product_risk": {
        "level": "info",
        "alerts": [],
        "trends": {
          "observations": 1
        },
        "automatic_replacement": false
      }
    },
    {
      "code": "513100",
      "name": "纳指ETF",
      "market_cap": 21412000000.0,
      "avg_turnover_20d": 1152800381.0,
      "turnover_1d": 590427457.0,
      "premium_pct": 12.22,
      "tracking_dispersion": null,
      "fee": {
        "management_fee": 0.006,
        "custody_fee": 0.002,
        "expense_ratio": 0.008
      },
      "purchase_status": "不可申购",
      "cross_validation": {
        "status": "partial",
        "sources": [
          "akshare",
          "westock"
        ],
        "fields": {
          "price": {
            "westock": 2.26,
            "akshare": 2.263,
            "threshold": 0.003,
            "difference": 0.00132567,
            "status": "verified"
          },
          "iopv": {
            "westock": 2.08,
            "akshare": 2.0165,
            "threshold": 0.005,
            "westock_basis": "published_nav",
            "akshare_basis": "realtime_iopv",
            "difference": 0.03052885,
            "status": "not_comparable"
          },
          "premium": {
            "westock": 0.08653846153846145,
            "akshare": 0.12224150756260843,
            "threshold": 0.005,
            "westock_basis": "published_nav",
            "akshare_basis": "realtime_iopv",
            "difference": 0.03570305,
            "status": "not_comparable"
          },
          "market_cap": {
            "westock": 21412000000.0,
            "akshare": 21421808559.0,
            "threshold": 0.15,
            "difference": 0.00045788,
            "status": "verified"
          }
        },
        "critical_conflicts": [],
        "scale_conflict": false
      },
      "product_events": [],
      "product_risk": {
        "level": "info",
        "alerts": [],
        "trends": {
          "observations": 1
        },
        "automatic_replacement": false
      }
    },
    {
      "code": "159915",
      "name": "创业板ETF",
      "market_cap": 44998000000.0,
      "avg_turnover_20d": 5634686333.0,
      "turnover_1d": 3758413071.0,
      "premium_pct": 0.03,
      "tracking_dispersion": null,
      "fee": {
        "management_fee": 0.0015,
        "custody_fee": 0.0005,
        "expense_ratio": 0.002
      },
      "purchase_status": "可申购",
      "cross_validation": {
        "status": "partial",
        "sources": [
          "akshare",
          "westock"
        ],
        "fields": {
          "price": {
            "westock": 4.28,
            "akshare": 4.277,
            "threshold": 0.003,
            "difference": 0.00070093,
            "status": "verified"
          },
          "iopv": {
            "westock": 4.12,
            "akshare": 4.2757,
            "threshold": 0.005,
            "westock_basis": "published_nav",
            "akshare_basis": "realtime_iopv",
            "difference": 0.03641509,
            "status": "not_comparable"
          },
          "premium": {
            "westock": 0.03883495145631066,
            "akshare": 0.0003040437823047526,
            "threshold": 0.005,
            "westock_basis": "published_nav",
            "akshare_basis": "realtime_iopv",
            "difference": 0.03853091,
            "status": "not_comparable"
          },
          "market_cap": {
            "westock": 44998000000.0,
            "akshare": 45008816932.0,
            "threshold": 0.15,
            "difference": 0.00024033,
            "status": "verified"
          }
        },
        "critical_conflicts": [],
        "scale_conflict": false
      },
      "product_events": [],
      "product_risk": {
        "level": "info",
        "alerts": [],
        "trends": {
          "observations": 1
        },
        "automatic_replacement": false
      }
    },
    {
      "code": "588000",
      "name": "科创50ETF",
      "market_cap": 65075000000.0,
      "avg_turnover_20d": 6397113656.0,
      "turnover_1d": 7086603587.0,
      "premium_pct": -0.05,
      "tracking_dispersion": null,
      "fee": {
        "management_fee": 0.0015,
        "custody_fee": 0.0005,
        "expense_ratio": 0.002
      },
      "purchase_status": "可申购",
      "cross_validation": {
        "status": "partial",
        "sources": [
          "akshare",
          "westock"
        ],
        "fields": {
          "price": {
            "westock": 2.03,
            "akshare": 2.027,
            "threshold": 0.003,
            "difference": 0.00147783,
            "status": "verified"
          },
          "iopv": {
            "westock": 1.85,
            "akshare": 2.0281,
            "threshold": 0.005,
            "westock_basis": "published_nav",
            "akshare_basis": "realtime_iopv",
            "difference": 0.08781618,
            "status": "not_comparable"
          },
          "premium": {
            "westock": 0.09729729729729719,
            "akshare": -0.0005423795670823628,
            "threshold": 0.005,
            "westock_basis": "published_nav",
            "akshare_basis": "realtime_iopv",
            "difference": 0.09783968,
            "status": "not_comparable"
          },
          "market_cap": {
            "westock": 65075000000.0,
            "akshare": 65011298360.0,
            "threshold": 0.15,
            "difference": 0.0009789,
            "status": "verified"
          }
        },
        "critical_conflicts": [],
        "scale_conflict": false
      },
      "product_events": [],
      "product_risk": {
        "level": "info",
        "alerts": [],
        "trends": {
          "observations": 1
        },
        "automatic_replacement": false
      }
    }
  ]
}